parallel_feature_selector.py
parallel_feature_selector-0.1.1.dist-info/LICENSE
parallel_feature_selector-0.1.1.dist-info/METADATA
parallel_feature_selector-0.1.1.dist-info/WHEEL
parallel_feature_selector-0.1.1.dist-info/top_level.txt
parallel_feature_selector-0.1.1.dist-info/RECORD
