Metadata-Version: 2.1
Name: parallel-feature-selector
Version: 0.1.1
Summary: Package for parallelized feature selection methods
Home-page: https://github.com/haeren/parallel-feature-selector
Author: haeren
Author-email: erenhalp@gmail.com
License: MIT
Platform: UNKNOWN
Classifier: Programming Language :: Python :: 3
Classifier: License :: OSI Approved :: MIT License
Classifier: Operating System :: OS Independent
Requires-Python: >=3.6
License-File: LICENSE
Requires-Dist: pandas
Requires-Dist: scikit-learn
Requires-Dist: mpi4py
Requires-Dist: arff2pandas
Requires-Dist: openpyxl
